README.txt
setup.py
src/mekk/__init__.py
src/mekk.rtmimport.egg-info/PKG-INFO
src/mekk.rtmimport.egg-info/SOURCES.txt
src/mekk.rtmimport.egg-info/dependency_links.txt
src/mekk.rtmimport.egg-info/entry_points.txt
src/mekk.rtmimport.egg-info/namespace_packages.txt
src/mekk.rtmimport.egg-info/not-zip-safe
src/mekk.rtmimport.egg-info/requires.txt
src/mekk.rtmimport.egg-info/top_level.txt
src/mekk/rtmimport/__init__.py
src/mekk/rtmimport/nozbe_import.py
src/mekk/rtmimport/rtm_updater.py
src/mekk/rtmimport/run.py