Metadata-Version: 1.0
Name: mekk.rtmimport
Version: 0.1.2
Summary: Import foreign (at the moment, Nozbe) data to RememberTheMilk
Home-page: UNKNOWN
Author: Marcin Kasperski
Author-email: Marcin.Kasperski@mekk.waw.pl
License: LGPL
Keywords: rtm,RememberTheMilk
Platform: UNKNOWN
Classifier: Programming Language :: Python
Classifier: Intended Audience :: Developers
Classifier: Topic :: Software Development :: Libraries :: Python Modules
